quickrspecpuppet
