Metadata-Version: 1.0
Name: quickrspecpuppet
Version: 0.1.1
Summary: quickrspecpuppet - Quickly create basic rspec tests for your puppet modules
Home-page: https://github.com/teriyakichild/quickrspecpuppet
Author: Tony Rogers
Author-email: tony.rogers@rackspace.com
License: ASLv2
Platform: UNKNOWN
